{
	"comment000" : "***************************************************************************",
	"comment001" : "****************BEGIN BASIC GEOS-CHEM AND ENSEMBLE SETTINGS****************",
	"comment002" : "***************************************************************************",
	"GC_VERSION" : "14.0.2",
	"RES" : "2.0x2.5",
	"met_name" : "MERRA2",
	"LEVS" : "47",
	"NEST" : "F",
	"REGION" : "",
	"ASSIM_PATH" : "/n/home12/drewpendergrass/CHEEREIO",
	"RUN_NAME" : "METHANE_scale_v06",
	"MY_PATH" : "/n/holyscratch01/jacob_lab/dpendergrass/GC-LETKF",
	"DATA_PATH" : "/n/holyscratch01/external_repos/GEOS-CHEM/gcgrid/gcdata/ExtData",
	"CH4_HEMCO_ROOT" : "/n/seasasfs02/CH4_inversion/InputData/HEMCO",
	"USE_CHEEREIO_TEMPLATE_CH4_HEMCO_Config" : "False",
	"RESTART_FILE" : "/n/holyscratch01/jacob_lab/dpendergrass/GC-LETKF/input_data/GEOSChem.BoundaryConditions.20180701_0000z.nc4",
	"BC_FILES" : "",
	"sim_name" : "CH4",
	"chemgrid" : "trop+strat",
	"sim_extra_option" : "none",
	"DO_SPINUP" : "false",
	"SPINUP_START" : "",
	"SPINUP_END" : "",
	"DO_CONTROL_RUN" : "true",
	"DO_CONTROL_WITHIN_ENSEMBLE_RUNS" : "true",
	"CONTROL_START" : "",
	"CONTROL_END" : "",
	"DO_ENS_SPINUP" : "true",
	"ENS_SPINUP_FROM_BC_RESTART" : "true",
	"ENS_SPINUP_START" : "20180701",
	"ENS_SPINUP_END" : "20181101",
	"START_DATE" : "20181101",
	"ASSIM_START_DATE" : "20181108",
	"SIMPLE_SCALE_FOR_FIRST_ASSIM_PERIOD" : "true",
	"END_DATE" : "20200101",
	"AMPLIFY_ENSEMBLE_SPREAD_FOR_FIRST_ASSIM_PERIOD" : "true",
	"SPREAD_AMPLIFICATION_FACTOR" : "5",
	"SIMPLE_SCALE_AT_END_OF_BURN_IN_PERIOD" : "true",
	"BURN_IN_END" : "20181225",
	"POSTPROCESS_START_DATE":"20190101",
	"POSTPROCESS_END_DATE":"20200101",
	"nEnsemble" : "24",
	"verbose":"1",
	"comment003" : "***************************************************************************",
	"comment004" : "***************************BEGIN CLUSTER SETTINGS**************************",
	"comment005" : "***************************************************************************",
	"NumCores" : "2",
	"NumCtrlCores" : "24",
	"Partition" : "huce_intel",
	"Memory" : "30000",
	"EnsCtrlSpinupMemory" : "8000",
	"WallTime" : "7-00\\:00",
	"EnsSpinupWallTime" : "1-00\\:00",
	"ControlWallTime" : "3-00\\:00",
	"SpinupWallTime" : "",
	"CondaEnv" : "cheerio",
	"AnimationEnv" : "geoplt_2",
	"MaxPar" : "2",
	"comment006" : "******************************************************************************",
	"comment007" : "****************SPECIFY BELOW SPECIES IN STATE/CONTROL VECTORS****************",
	"comment008" : "******************************************************************************",
	"STATE_VECTOR_CONC" : [
		"CH4"
	],
	"CONTROL_VECTOR_CONC" : [
		"CH4"
	],
	"STATE_VECTOR_CONC_REPRESENTATION" : "3D",
	"CONTROL_VECTOR_EMIS" : {
		"CH4":"CH4"
	},
	"comment009" : "******************************************************************************",
	"comment010" : "**********************SPECIFY BELOW HISTORY.RC SETTINGS**********************",
	"comment011" : "******************************************************************************",
	"HISTORY_collections_to_customize" : [
		"SpeciesConc",
		"CH4",
		"LevelEdgeDiags",
		"StateMet",
		"Restart"
	],
	"HISTORY_freq" : "00000000 040000",
	"HISTORY_dur" : "00000001 000000",
	"SPINUP_HISTORY_freq" : "00000100 000000",
	"SPINUP_HISTORY_dur" : "00000100 000000",
	"SaveLevelEdgeDiags" : "True",
	"SaveStateMet" : "False",
	"SaveArea" : "False",
	"HistorySpeciesConcToSave" : [
		"CH4"
	],
	"HistoryLevelEdgeDiagsToSave" : [
		"Met_PEDGE"
	],
	"HistoryRestartToSave" : [
		"SpeciesRst_?ALL?",
		"Met_PS1DRY",
		"Met_TMPU1",
		"Met_BXHEIGHT",
		"Met_TropLev"
	],
	"HistoryStateMetToSave" : [
		"Met_AD"
	],
	"comment012" : "******************************************************************************",
	"comment013" : "**********************SPECIFY BELOW OBSERVATION SETTINGS**********************",
	"comment014" : "******************************************************************************",
	"OBSERVED_SPECIES" : {
		"CH4_TROPOMI": "CH4"
	},
	"OBS_TYPE" : {
		"CH4_TROPOMI":"TROPOMI"
	},
	"TROPOMI_dirs" : {
		"CH4" : "/n/jacob_lab/Lab/seasasfs02/CH4_inversion/InputData/Obs/TROPOMI"
	},
	"OMI_dirs" : {
		"NO2" : "/n/holylfs05/LABS/jacob_lab/dpendergrass/omi/NO2"
	},
	"filter_obs_poleward_of_n_degrees" : {
		"CH4_TROPOMI":"60"
	},
	"SaveDOFS" : "False",
	"DOFS_filter" : "1",
	"comment015" : "******************************************************************************",
	"comment016" : "********************SPECIFY BELOW SCALING FACTOR SETTINGS*********************",
	"comment017" : "******************************************************************************",
	"pPERT" : {
		"CH4":"0.1"
	},
	"pertType" : {
		"CH4":"std"
	},
	"correlatedInitialScalings" : {
		"CH4":"True"
	},
	"corrDistances" : {
		"CH4":"500"
	},
	"speedyCorrelationApprox" : "True",
	"lognormalErrors" : "True",
	"MaskOceanScaleFactor" : {
		"CH4":"True"
	},
	"MaskCoastsGT25pctOcean" : "True",
	"Mask60NScaleFactor" : {
		"CH4":"False"
	},
	"Mask60SScaleFactor" : {
		"CH4":"True"
	},
	"MinimumScalingFactorAllowed" : {
		"CH4":"0"
	},
	"MaximumScalingFactorAllowed" : {
		"CH4":"nan"
	},
	"InflateScalingsToXOfInitialStandardDeviation" : {
		"CH4":"nan"
	},
	"MaximumScaleFactorRelativeChangePerAssimilationPeriod" : {
		"CH4":"nan"
	},
	"comment018" : "******************************************************************************",
	"comment019" : "*************************SPECIFY BELOW LETKF SETTINGS*************************",
	"comment020" : "******************************************************************************",
	"REGULARIZING_FACTOR_GAMMA": {
		"CH4_TROPOMI":"1"
	},
	"USE_DIFFERENT_GAMMA_FOR_BURN_IN" : {
		"CH4_TROPOMI":"True"
	},
	"GAMMA_FOR_BURN_IN" : {
		"CH4_TROPOMI":"5"
	},
	"OBS_ERROR": {
		"CH4_TROPOMI":"17"
	},
	"OBS_ERROR_TYPE":{
		"CH4_TROPOMI":"absolute"
	},
	"OBS_ERROR_SELF_CORRELATION" : {
		"CH4_TROPOMI":"0.28"
	},
	"MIN_OBS_ERROR":{
		"CH4_TROPOMI":"10"
	},
	"OTHER_OBS_ERROR_PARAMETERS":{
		"CH4_TROPOMI":{
			"transport_error":"6.1"
		}
	},
	"AV_TO_GC_GRID" : "True",
	"SUPER_OBSERVATION_FUNCTION":{
		"CH4_TROPOMI":"default"
	},
	"INFLATION_FACTOR": "0.03",
	"ASSIM_TIME": "168",
	"MAXNUMOBS" : "3000",
	"MINNUMOBS" : "1",
	"LOCALIZATION_RADIUS_km" : "500",
	"AveragePriorAndPosterior" : "False",
	"PriorWeightinPriorPosteriorAverage" : "0.5",
	"comment021" : "**********************************************************************************",
	"comment022" : "******************************BEGIN POSTPROCESS SETTINGS***************************",
	"comment023" : "**********************************************************************************",
	"animation_fps_scalingfactor":"2",
	"animation_fps_concentrations":"18",
	"hemco_diags_to_process" : [
		"EmisCH4_Total"
	],
	"min_emis_value_to_plot" : "1e-14",
	"min_emis_std_value_to_plot" : "1e-15",
	"OBSERVATION_UNITS":{
		"CH4_TROPOMI": "ppb"
	},
	"scalefactor_plot_freq" : "monthly",
	"comment021" : "**********************************************************************************",
	"comment022" : "******************************BEGIN SETTING EXTENSIONS****************************",
	"comment023" : "**********************************************************************************",
	"Extensions": {
		"TROPOMI_ALL":"True",
		"TROPOMI_CH4":"True",
		"CH4":"True"
	}
}